requirements_tools/__init__.py
requirements_tools/check_all_wheels.py
requirements_tools/check_requirements.py
requirements_tools/upgrade_requirements.py
requirements_tools/visualize_requirements.py
requirements_tools-2.1.0.dist-info/LICENSE
requirements_tools-2.1.0.dist-info/METADATA
requirements_tools-2.1.0.dist-info/WHEEL
requirements_tools-2.1.0.dist-info/entry_points.txt
requirements_tools-2.1.0.dist-info/top_level.txt
requirements_tools-2.1.0.dist-info/RECORD
